<?xml version="1.0" encoding="UTF-8"?>
<!DOCTYPE suite SYSTEM "http://testng.org/testng-1.0.dtd">
<suite name="checkoutjs suite">
    <test name="PGP-41842">
        <parameter name="theme" value="checkoutjs_web_revamp"/>
        <classes>
            <class name="scripts.Native.checkoutjs.CheckoutJsTests">
                <methods>
                    <include name="Verify_bankResultInfo_parameter_enabled_when_transaction_failed_for_offline_merchant_in_theia_merchantStatus_logs"/>
                </methods>
            </class>
        </classes>
    </test>
</suite>