<?xml version="1.0" encoding="UTF-8"?>
<!DOCTYPE suite SYSTEM "http://testng.org/testng-1.0.dtd">
<suite name="SavedCard" verbose="1" parallel="tests" thread-count="1">
    <test name="NEW SAVED CARD API">
        <parameter name="theme" value="enhancedweb_revamp"/>
        <classes>
            <class name="scripts.Native.FetchBinDetails">
                <methods>
                    <include name="validateGetBinBulkHashForBulkCardBins"/>
                </methods>
            </class>
        </classes>
    </test>
</suite>